{
  "schema_version": "1.0",
  "product_id": "8116032536633",
  "source": "shopify",
  "source_url": "https://goodfair1.myshopify.com",
  "handle": "new-womens-bamboo-padded-sports-bra-in-black",
  "title": "New Women's Bamboo Padded Sports Bra in Black",
  "vendor": "Spun Bamboo",
  "product_type": "sport bra",
  "description": "<p>Support, style, and beauty all in one. One, two, and three layers of fabric strategically placed allow for support along with freedom of movement. Some prefer to use the bra for yoga and stretching, and others use the bra for higher-impact activities like running and aerobics. As for sizing, for example, a 34B may prefer a small for running or playing sports to give the best support; but, during yoga or biking, a medium may give the best comfort/performance ratio. Removable pads for extra support. Think Nike brand sizing and best-style underwear. Women's yoga tights are available in a variety of materials, including bamboo clothing and organic cotton. <br>Made of 70% viscose from bamboo, 20% organic cotton, and 10% spandex. Sizes: S, M, L, XL, XXL.</p>\n<p>•Bamboo yoga is a popular form of exercise that has gained traction in recent years.<br data-mce-fragment=\"1\">•Bamboo yoga pants are an excellent choice for those looking for comfortable yet stylish apparel while practicing or attending classes.</p>\n<p><br>Designed in California, and made in China.</p>\n<p> </p>",
  "pricing": {
    "currency": "INR",
    "min_price": 29.39,
    "max_price": 29.39
  },
  "variants": [
    {
      "variant_id": "45247192039481",
      "title": "Small / Black",
      "price": 29.39,
      "available": false,
      "sku": "ET-JPB-SMA-BLA"
    },
    {
      "variant_id": "45247192072249",
      "title": "Medium / Black",
      "price": 29.39,
      "available": false,
      "sku": "ET-JPB-MED-BLA"
    },
    {
      "variant_id": "45247192105017",
      "title": "Large / Black",
      "price": 29.39,
      "available": true,
      "sku": "ET-JPB-LAR-BLA"
    },
    {
      "variant_id": "45247192137785",
      "title": "Extra Large / Black",
      "price": 29.39,
      "available": true,
      "sku": "ET-JPB-XLA-BLA"
    },
    {
      "variant_id": "45247192170553",
      "title": "XX-Large / Black",
      "price": 29.39,
      "available": false,
      "sku": "ET-JPB-XXL-BLA"
    }
  ],
  "images": [
    {
      "url": "https://cdn.shopify.com/s/files/1/0077/1745/3881/files/branew.png?v=1765910894",
      "alt_text": null
    },
    {
      "url": "https://cdn.shopify.com/s/files/1/0077/1745/3881/files/womens-bamboocotton-sports-bra-in-black-sport-bra-spun-bamboo-436193_d8a6b786-9b80-42ea-ba7c-7c258f014edc.jpg?v=1765479089",
      "alt_text": null
    },
    {
      "url": "https://cdn.shopify.com/s/files/1/0077/1745/3881/files/womens-bamboocotton-sports-bra-in-black-sport-bra-spun-bamboo-440200_a751f43f-dd8d-4a71-a0b8-c05417e861a4.jpg?v=1765479089",
      "alt_text": null
    },
    {
      "url": "https://cdn.shopify.com/s/files/1/0077/1745/3881/files/womens-bamboocotton-sports-bra-in-black-sport-bra-spun-bamboo-322420_8ec15c37-ad3c-4d76-9ac0-235d4f720388.jpg?v=1765479089",
      "alt_text": null
    },
    {
      "url": "https://cdn.shopify.com/s/files/1/0077/1745/3881/files/womens-bamboocotton-sports-bra-in-black-sport-bra-spun-bamboo-433858_024d2c47-719a-40d8-8f10-b2b33fa9dbee.jpg?v=1765479090",
      "alt_text": null
    },
    {
      "url": "https://cdn.shopify.com/s/files/1/0077/1745/3881/files/womens-bamboocotton-sports-bra-in-black-sport-bra-spun-bamboo-312013_604262de-795f-4dca-a6cc-651b12143bd3.jpg?v=1765479090",
      "alt_text": null
    }
  ],
  "availability": {
    "in_stock": true,
    "total_variants": 5,
    "available_variants": 2
  },
  "metadata": {
    "created_at": "2025-12-11T13:51:27-05:00",
    "ingested_at": "2026-01-30T12:29:15.515906+00:00"
  }
}