{
  "schema_version": "1.0",
  "product_id": "8117509259321",
  "source": "shopify",
  "source_url": "https://goodfair1.myshopify.com",
  "handle": "hailey-brook-designs-32oz-or-40oz-sublimation-clear-or-frost-glass-tumbler-mug-cup-with-bamboo-lid-and-straw",
  "title": "Hailey Brook Designs 32oz or 40oz Sublimation Clear or Frost Glass Tumbler, Mug, Cup With Bamboo Lid and Straw",
  "vendor": "Hailey Brook Designs",
  "product_type": "Tumblers",
  "description": "<p>These Sublimation Glass Tumbler are perfect for enjoying your favorite beverage in style. this tumbler comes in your choice of clear or frost glass, giving you the option to choose the look you like best.</p>\n<p>Leak-proof and round-shaped, this tumbler is designed to be both functional and stylish. It comes with a bamboo lid and plastic straw for added convenience when enjoying your drink on-the-go.</p>\n<p>The blank pattern allows you to customize the tumbler with any design of your choosing using sublimation printing techniques.</p>\n<p>With one tumbler included per pack, this product makes for a great gift idea or personal purchase. It also comes in a retail box packaging making it easy to gift wrap.</p>\n<p>Upgrade your drinkware collection today with this stylish Sublimation Glass Tumbler!</p>\n<p>NOTE:<br><span>**Hand Wash recommended*** No heat Drying*** </span></p>",
  "pricing": {
    "currency": "INR",
    "min_price": 12.99,
    "max_price": 19.99
  },
  "variants": [
    {
      "variant_id": "45251616178233",
      "title": "32oz Clear Glass Bamboo Lid",
      "price": 14.99,
      "available": true,
      "sku": "32GCD"
    },
    {
      "variant_id": "45251616211001",
      "title": "32oz Frost Glass Bamboo Lid",
      "price": 12.99,
      "available": true,
      "sku": "32GFD"
    },
    {
      "variant_id": "45251616243769",
      "title": "40oz Clear Glass Bamboo Lid",
      "price": 16.99,
      "available": true,
      "sku": "G40OZC"
    },
    {
      "variant_id": "45251616276537",
      "title": "40oz Frost Glass Bamboo Lid",
      "price": 16.99,
      "available": true,
      "sku": "G40OZF"
    },
    {
      "variant_id": "45251616309305",
      "title": "32oz Clear Glass Plastic Lid",
      "price": 18.99,
      "available": true,
      "sku": "32PLIDC"
    },
    {
      "variant_id": "45251616342073",
      "title": "32oz Frost Glass Plastic Lid",
      "price": 19.99,
      "available": true,
      "sku": "32PLIDF"
    },
    {
      "variant_id": "45251616374841",
      "title": "40oz Clear Glass Plastic Lid",
      "price": 18.99,
      "available": true,
      "sku": "40PLIDC"
    },
    {
      "variant_id": "45251616407609",
      "title": "40oz Frost Glass Plastic Lid",
      "price": 18.99,
      "available": true,
      "sku": "40PLIDF"
    }
  ],
  "images": [
    {
      "url": "https://cdn.shopify.com/s/files/1/0077/1745/3881/files/DE483CD7-EC91-4C67-9155-A8628F6A48E3_4aa26271-10e3-4fd0-98e0-90ea16971e34.jpg?v=1765908832",
      "alt_text": null
    },
    {
      "url": "https://cdn.shopify.com/s/files/1/0077/1745/3881/files/IMG_8730_b86e6757-f640-4e35-a86c-20af84d34264.jpg?v=1765650042",
      "alt_text": null
    },
    {
      "url": "https://cdn.shopify.com/s/files/1/0077/1745/3881/files/IMG_9336.jpg?v=1765650041",
      "alt_text": null
    },
    {
      "url": "https://cdn.shopify.com/s/files/1/0077/1745/3881/files/IMG_9337.jpg?v=1765650041",
      "alt_text": null
    },
    {
      "url": "https://cdn.shopify.com/s/files/1/0077/1745/3881/files/IMG_8731_d1027ae7-949e-40e8-b810-40efc117d088.jpg?v=1765650042",
      "alt_text": null
    },
    {
      "url": "https://cdn.shopify.com/s/files/1/0077/1745/3881/files/IMG_8734_58a9d2b7-e395-4683-9dc3-e9274c0d4dfe.jpg?v=1765650040",
      "alt_text": null
    },
    {
      "url": "https://cdn.shopify.com/s/files/1/0077/1745/3881/files/IMG_8733_f51d0599-5c7f-47fc-9278-e55cd99767cb.jpg?v=1765650041",
      "alt_text": null
    },
    {
      "url": "https://cdn.shopify.com/s/files/1/0077/1745/3881/files/IMG_8732_f78fbbb0-30b1-4f9d-ada1-584342879bb4.jpg?v=1765650041",
      "alt_text": null
    }
  ],
  "availability": {
    "in_stock": true,
    "total_variants": 8,
    "available_variants": 8
  },
  "metadata": {
    "created_at": "2025-12-13T13:20:38-05:00",
    "ingested_at": "2026-01-30T12:29:15.485401+00:00"
  }
}